uncleprofile
